{
  "gitSyncId": "6833bd1e663f59025c630a90_eee843d4-0cea-4c2e-a500-de5fbfbe31fb",
  "unpublishedPage": {
    "isHidden": false,
    "layouts": [
      {
        "dsl": {
          "backgroundColor": "none",
          "bottomRow": 1330,
          "canExtend": true,
          "containerStyle": "none",
          "detachFromLayout": true,
          "dynamicBindingPathList": [],
          "leftColumn": 0,
          "minHeight": 760,
          "parentColumnSpace": 1,
          "parentRowSpace": 1,
          "rightColumn": 1224,
          "snapColumns": 64,
          "snapRows": 74,
          "topRow": 0,
          "type": "CANVAS_WIDGET",
          "version": 93,
          "widgetId": "0",
          "widgetName": "MainContainer"
        }
      }
    ],
    "name": "IVPData Copy",
    "slug": "ivpdata-copy"
  }
}